README.md
setup.cfg
setup.py
sensitive/__init__.py
sensitive/error_posix.py
sensitive/error_win.py
sensitive/test.py
sensitive_test.egg-info/PKG-INFO
sensitive_test.egg-info/SOURCES.txt
sensitive_test.egg-info/dependency_links.txt
sensitive_test.egg-info/top_level.txt