Metadata-Version: 2.1
Name: sensitive-test
Version: 1.0.1
Summary: A small, simple, and fast ordered failfast test-suite for Python.
Home-page: UNKNOWN
Author: vierofernando
Author-email: vierofernando9@gmail.com
License: MIT
Keywords: test,tests,ci,debug
Platform: UNKNOWN
Classifier: Development Status :: 4 - Beta
Classifier: Intended Audience :: Developers
Classifier: Topic :: Software Development :: Build Tools
Classifier: License :: OSI Approved :: MIT License
Classifier: Programming Language :: Python :: 3.7
Classifier: Programming Language :: Python :: 3.8
Classifier: Programming Language :: Python :: 3.9
Requires-Python: >=3.6
